peewee_moves.py
peewee_moves-2.1.0.dist-info/LICENSE
peewee_moves-2.1.0.dist-info/METADATA
peewee_moves-2.1.0.dist-info/WHEEL
peewee_moves-2.1.0.dist-info/entry_points.txt
peewee_moves-2.1.0.dist-info/top_level.txt
peewee_moves-2.1.0.dist-info/RECORD
