Metadata-Version: 1.1
Name: peewee-moves
Version: 2.1.0
Summary: Simple and flexible migration manager for Peewee ORM.
Home-page: https://github.com/timster/peewee-moves
Author: Tim Shaffer
Author-email: timshaffer@me.com
License: MIT
Keywords: peewee orm database migration development
Platform: UNKNOWN
Classifier: Development Status :: 3 - Alpha
Classifier: Intended Audience :: Developers
Classifier: Topic :: Database :: Front-Ends
Classifier: License :: OSI Approved :: MIT License
Classifier: Programming Language :: Python :: 3.4
Classifier: Programming Language :: Python :: 3.5
Classifier: Programming Language :: Python :: 3.6
